{
  "date": "2026-01-21",
  "username": "naitik-makwana-yral",
  "additions": 1463,
  "deletions": 68,
  "total_loc": 1531,
  "commit_count": 4,
  "repositories": [
    "dolr-ai/hot-or-not-web-leptos-ssr",
    "dolr-ai/off-chain-agent"
  ],
  "repo_count": 2,
  "branch_breakdown": {
    "dolr-ai/off-chain-agent": {
      "main": {
        "additions": 665,
        "deletions": 19,
        "total_loc": 684,
        "commit_count": 1
      },
      "naitik/migrate_fly_redis_to_dragonfly": {
        "additions": 5,
        "deletions": 5,
        "total_loc": 10,
        "commit_count": 1
      }
    },
    "dolr-ai/hot-or-not-web-leptos-ssr": {
      "main": {
        "additions": 793,
        "deletions": 44,
        "total_loc": 837,
        "commit_count": 1
      },
      "naitik/migrate_reads_to_dragonfly": {
        "additions": 0,
        "deletions": 0,
        "total_loc": 0,
        "commit_count": 1
      }
    }
  },
  "processed_at": "2026-02-06T07:06:58.955470Z"
}