{
  "date": "2026-02-10",
  "username": "kevin-antony-yral",
  "additions": 2227,
  "deletions": 606,
  "total_loc": 2833,
  "commit_count": 4,
  "repositories": [
    "dolr-ai/yral-ai-chat"
  ],
  "repo_count": 1,
  "branch_breakdown": {
    "dolr-ai/yral-ai-chat": {
      "db_mig": {
        "additions": 1950,
        "deletions": 587,
        "total_loc": 2537,
        "commit_count": 2
      },
      "main": {
        "additions": 277,
        "deletions": 19,
        "total_loc": 296,
        "commit_count": 2
      }
    }
  },
  "processed_at": "2026-02-11T15:05:54.371561Z"
}